LICENSE
MANIFEST.in
README.md
setup.py
rest_fastapi/__init__.py
rest_fastapi/builder_api.py
rest_fastapi/log_settings.py
rest_fastapi/main.py
rest_fastapi/settings.conf
rest_fastapi/sqlit.db
rest_fastapi.egg-info/PKG-INFO
rest_fastapi.egg-info/SOURCES.txt
rest_fastapi.egg-info/dependency_links.txt
rest_fastapi.egg-info/requires.txt
rest_fastapi.egg-info/top_level.txt
rest_fastapi/bases/__init__.py
rest_fastapi/bases/dao.py
rest_fastapi/bases/enums.py
rest_fastapi/bases/model.py
rest_fastapi/bases/schema.py
rest_fastapi/bases/service.py
rest_fastapi/core/__init__.py
rest_fastapi/core/db/__init__.py
rest_fastapi/core/db/mysql.py
rest_fastapi/demo_api/__init__.py
rest_fastapi/demo_api/enums.py
rest_fastapi/demo_api/controllers/__init__.py
rest_fastapi/demo_api/controllers/dome.py
rest_fastapi/demo_api/daos/__init__.py
rest_fastapi/demo_api/daos/dome.py
rest_fastapi/demo_api/models/__init__.py
rest_fastapi/demo_api/models/demo.py
rest_fastapi/demo_api/schemas/__init__.py
rest_fastapi/demo_api/schemas/demo.py
rest_fastapi/demo_api/services/__init__.py
rest_fastapi/demo_api/services/demo.py
rest_fastapi/libs/__init__.py
rest_fastapi/libs/data_time.py
rest_fastapi/libs/excel_tool.py
rest_fastapi/libs/exceptions.py
rest_fastapi/libs/pagination.py