Metadata-Version: 2.1
Name: rest-fastapi
Version: 0.1.5
Summary: fastapi脚手架，封装了基本curd
Home-page: https://gitee.com/ileona/falsework.git
Author: lxshen
Author-email: lxshen613@163.com
Classifier: Programming Language :: Python :: 3
Classifier: License :: OSI Approved :: MIT License
Classifier: Operating System :: OS Independent
Requires-Python: >=3.8.15
License-File: LICENSE
